MANIFEST.in
README.md
pyproject.toml
setup.py
.pixi/envs/default/lib/python3.1/site-packages/debugpy/_vendored/pydevd/pydevd_attach_to_process/common/py_custom_pyeval_settrace.hpp
.pixi/envs/default/lib/python3.1/site-packages/debugpy/_vendored/pydevd/pydevd_attach_to_process/common/py_custom_pyeval_settrace_310.hpp
.pixi/envs/default/lib/python3.1/site-packages/debugpy/_vendored/pydevd/pydevd_attach_to_process/common/py_custom_pyeval_settrace_311.hpp
.pixi/envs/default/lib/python3.1/site-packages/debugpy/_vendored/pydevd/pydevd_attach_to_process/common/py_custom_pyeval_settrace_common.hpp
.pixi/envs/default/lib/python3.1/site-packages/debugpy/_vendored/pydevd/pydevd_attach_to_process/common/py_settrace.hpp
.pixi/envs/default/lib/python3.1/site-packages/debugpy/_vendored/pydevd/pydevd_attach_to_process/common/py_utils.hpp
.pixi/envs/default/lib/python3.1/site-packages/debugpy/_vendored/pydevd/pydevd_attach_to_process/common/py_version.hpp
.pixi/envs/default/lib/python3.1/site-packages/debugpy/_vendored/pydevd/pydevd_attach_to_process/common/ref_utils.hpp
.pixi/envs/default/lib/python3.1/site-packages/debugpy/_vendored/pydevd/pydevd_attach_to_process/linux_and_mac/attach.cpp
.pixi/envs/default/lib/python3.1/site-packages/debugpy/_vendored/pydevd/pydevd_attach_to_process/windows/attach.cpp
.pixi/envs/default/lib/python3.1/site-packages/debugpy/_vendored/pydevd/pydevd_attach_to_process/windows/inject_dll.cpp
.pixi/envs/default/lib/python3.1/site-packages/debugpy/_vendored/pydevd/pydevd_attach_to_process/windows/py_win_helpers.hpp
.pixi/envs/default/lib/python3.1/site-packages/debugpy/_vendored/pydevd/pydevd_attach_to_process/windows/run_code_in_memory.hpp
.pixi/envs/default/lib/python3.1/site-packages/debugpy/_vendored/pydevd/pydevd_attach_to_process/windows/run_code_on_dllmain.cpp
.pixi/envs/default/lib/python3.1/site-packages/debugpy/_vendored/pydevd/pydevd_attach_to_process/windows/stdafx.cpp
py_stringcompare.egg-info/PKG-INFO
py_stringcompare.egg-info/SOURCES.txt
py_stringcompare.egg-info/dependency_links.txt
py_stringcompare.egg-info/requires.txt
py_stringcompare.egg-info/top_level.txt
