Metadata-Version: 2.4
Name: py-stringcompare
Version: 0.2.2
Summary: Efficient string comparison functions.
Home-page: https://github.com/OlivierBinette/StringCompare
Author: Olivier Binette
Author-email: olivier.binette@gmail.com
Keywords: record-linkage,string-distance,edit-distance,levenshtein,string-matching
Requires-Python: >=3.8
Requires-Dist: numpy<3,>=1
Requires-Dist: pybind11<4,>=2.4
Dynamic: author
Dynamic: author-email
Dynamic: home-page
Dynamic: keywords
Dynamic: requires-dist
Dynamic: requires-python
Dynamic: summary
